LICENSE
README.md
setup.py
bokeh_garden/__init__.py
bokeh_garden/annotation_pan_tool.py
bokeh_garden/annotation_wheel_zoom_tool.py
bokeh_garden/application.py
bokeh_garden/autocomplete.py
bokeh_garden/collection.py
bokeh_garden/compiler_cache.py
bokeh_garden/custom_action_tool.py
bokeh_garden/download.py
bokeh_garden/image.py
bokeh_garden/interactive_color_bar.py
bokeh_garden/latex_label.py
bokeh_garden/logging_bg.py
bokeh_garden/logging_handler.py
bokeh_garden/manual_log_entry.py
bokeh_garden/plot_collection.py
bokeh_garden/progress_bar.py
bokeh_garden/select.py
bokeh_garden/serverutils.py
bokeh_garden/tabs.py
bokeh_garden/upload.py
bokeh_garden.egg-info/PKG-INFO
bokeh_garden.egg-info/SOURCES.txt
bokeh_garden.egg-info/dependency_links.txt
bokeh_garden.egg-info/requires.txt
bokeh_garden.egg-info/top_level.txt
examples/__init__.py
examples/grib_info_download.py
examples/grib_plot.py
examples/grib_upload.py
examples/weather_data_explorer.py
examples/weather_data_explorer_pycharm_main.py