Metadata-Version: 2.1
Name: bokeh-garden
Version: 0.0.14
Summary: Additional widgets for Bokeh
Home-page: https://github.com/EMeraldGeo/BokehGarden
Author: Egil Moeller
Author-email: em@emeraldgeo.no
License-File: LICENSE
